climix/__init__.py
climix/aggregators.py
climix/dask_take_along_axis.py
climix/index.py
climix/index_docs.py
climix/iris.py
climix/main.py
climix/metadata.py
climix/period.py
climix/etc/config.yml
climix/etc/index_definitions.yml
climix/etc/indices.md.jinja
climix/etc/metadata.yml
climix/etc/variables.yml
climix/index_functions/__init__.py
climix/index_functions/index_functions.py
climix/index_functions/percentile_functions.py
climix/index_functions/spell_functions.py
climix/index_functions/spell_kernels.py
climix/index_functions/support.py
climix-0.24.1.dist-info/licenses/LICENSE
climix-0.24.1.dist-info/METADATA
climix-0.24.1.dist-info/WHEEL
climix-0.24.1.dist-info/entry_points.txt
climix-0.24.1.dist-info/top_level.txt
climix-0.24.1.dist-info/RECORD
