Metadata-Version: 2.4
Name: climix
Version: 0.24.1
Summary: A climate index package
Author-email: Lars Bärring <lars.barring@smhi.se>, Klaus Zimmermann <klaus.zimmermann@smhi.se>, Joakim Löw <joakim.low@smhi.se>, Carolina Nilsson <carolina.nilsson@smhi.se>
License-Expression: Apache-2.0
Project-URL: Homepage, https://git.smhi.se/climix/climix
Project-URL: Bug Reports, https://git.smhi.se/climix/climix/issues
Project-URL: Source, https://git.smhi.se/climix/climix
Classifier: Development Status :: 4 - Beta
Classifier: Environment :: Console
Classifier: Intended Audience :: Financial and Insurance Industry
Classifier: Intended Audience :: Science/Research
Classifier: Operating System :: OS Independent
Classifier: Programming Language :: Python :: 3.11
Classifier: Programming Language :: Python :: 3.12
Classifier: Programming Language :: Python :: 3.13
Classifier: Programming Language :: Python :: 3.14
Classifier: Topic :: Scientific/Engineering
Classifier: Topic :: Scientific/Engineering :: GIS
Requires-Python: >=3.11
License-File: LICENSE
Requires-Dist: cftime
Requires-Dist: cf-units
Requires-Dist: dask>=2023.1.0
Requires-Dist: distributed>=2023.1.0
Requires-Dist: gordias>0.3.0
Requires-Dist: numba
Requires-Dist: platformdirs
Requires-Dist: numpy
Requires-Dist: PyYAML
Requires-Dist: regex
Requires-Dist: scitools-iris<4,>=3
Requires-Dist: sparse
Dynamic: license-file
